odoo/addons/base_unece/README.rst
odoo/addons/base_unece/__init__.py
odoo/addons/base_unece/__manifest__.py
odoo/addons/base_unece/i18n/base_unece.pot
odoo/addons/base_unece/models/__init__.py
odoo/addons/base_unece/models/unece_code_list.py
odoo/addons/base_unece/readme/CONFIGURE.rst
odoo/addons/base_unece/readme/CONTRIBUTORS.rst
odoo/addons/base_unece/readme/DESCRIPTION.rst
odoo/addons/base_unece/security/ir.model.access.csv
odoo/addons/base_unece/static/description/icon.png
odoo/addons/base_unece/static/description/index.html
odoo/addons/base_unece/views/unece_code_list.xml
odoo12_addon_base_unece-12.0.1.1.0.dist-info/METADATA
odoo12_addon_base_unece-12.0.1.1.0.dist-info/WHEEL
odoo12_addon_base_unece-12.0.1.1.0.dist-info/top_level.txt
odoo12_addon_base_unece-12.0.1.1.0.dist-info/RECORD
